DCMIRead/__init__.py
DCMIRead/dicom_reader.py
DCMIRead-0.2.data/scripts/dicom_reader.py
DCMIRead-0.2.dist-info/METADATA
DCMIRead-0.2.dist-info/WHEEL
DCMIRead-0.2.dist-info/top_level.txt
DCMIRead-0.2.dist-info/RECORD
