Metadata-Version: 2.1
Name: DCMIRead
Version: 0.2
Summary: A package to read and normalize DICOM images
Home-page: https://github.com/WiseGeorge/DCMIRead
Author: Jorge Felix Martinez
Author-email: jorgito16040@gmail.com
License: UNKNOWN
Platform: UNKNOWN
Classifier: Programming Language :: Python :: 3
Classifier: License :: OSI Approved :: MIT License
Classifier: Operating System :: OS Independent
